sfhunter/__init__.py
sfhunter/cli.py
sfhunter/core.py
sfhunter-1.1.0.dist-info/licenses/LICENSE
sfhunter-1.1.0.dist-info/METADATA
sfhunter-1.1.0.dist-info/WHEEL
sfhunter-1.1.0.dist-info/entry_points.txt
sfhunter-1.1.0.dist-info/top_level.txt
sfhunter-1.1.0.dist-info/RECORD
